{
  "ColorDiffuse": {
    "a": 0.7451,
    "b": 0.5453,
    "g": 0.5453,
    "r": 0.5453
  },
  "Description": "horizontal border left",
  "GUID": "8646eb",
  "Hands": false,
  "HideWhenFaceDown": false,
  "Locked": true,
  "Name": "BlockRectangle",
  "Nickname": "Table Divider",
  "Tags": [
    "CameraZoom_ignore",
    "CleanUpHelper_ignore",
    "displacement_excluded",
    "NotInteractable"
  ],
  "Tooltip": false,
  "Transform": {
    "posX": -32.004,
    "posY": 1.5,
    "posZ": 79.5,
    "scaleX": 0.25,
    "scaleY": 0.1,
    "scaleZ": 17
  }
}
