{
  "AltLookAngle": {
    "x": 0,
    "y": 0,
    "z": 0
  },
  "Autoraise": true,
  "CardID": 1202900,
  "CustomDeck": {
    "12029": {
      "BackIsHidden": true,
      "BackURL": "https://steamusercontent-a.akamaihd.net/ugc/2342503777940352139/A2D42E7E5C43D045D72CE5CFC907E4F886C8C690/",
      "FaceURL": "https://steamusercontent-a.akamaihd.net/ugc/13494564998947083542/2ABAB8017A3C23FA7DAD4E36C6F2D4BFC3E3ADA3/",
      "NumHeight": 1,
      "NumWidth": 1,
      "Type": 0,
      "UniqueBack": false
    }
  },
  "Description": "",
  "DragSelectable": true,
  "GMNotes_path": "AllPlayerCards.15bb07/WinchesterModel125.12029.gmnotes",
  "GUID": "12029",
  "Grid": true,
  "GridProjection": false,
  "IgnoreFoW": false,
  "LayoutGroupSortIndex": 0,
  "Locked": false,
  "LuaScript": "",
  "LuaScriptState": "",
  "MeasureMovement": false,
  "Name": "Card",
  "Nickname": "Winchester Model 12 (5)",
  "Snap": true,
  "Sticky": true,
  "Tags": [
    "Asset",
    "PlayerCard"
  ],
  "Tooltip": true,
  "Transform": {
    "posX": 0,
    "posY": 0,
    "posZ": 0,
    "rotX": 0,
    "rotY": 270,
    "rotZ": 0,
    "scaleX": 1,
    "scaleY": 1,
    "scaleZ": 1
  },
  "Value": 0,
  "XmlUI": ""
}
